{
  "appid": "echoesofthefuture",
  "author": {
    "name": "DaReInt"
  },
  "category": "Games",
  "description": "Echoes of the Future is an interactive fiction adventure written in Inform 6 using the PunyInform library, specially designed for 8-bit computers and retro systems such as the Commodore 64.",
  "name": "Echoes of the Future",
  "url": {
    "source": "https://dareint.itch.io/echoes-of-the-future",
    "website": "https://dareint.itch.io/echoes-of-the-future",
    "x16forum": "https://dareint.itch.io/echoes-of-the-future"
  },
  "version": ""
}